LICENSE
vault/__init__.py
vault/client.py
vault/config.py
vault/exceptions.py
vault/utils.py
vault/vault.py
py_sec_vault-0.1.6.dist-info/LICENSE
py_sec_vault-0.1.6.dist-info/METADATA
py_sec_vault-0.1.6.dist-info/WHEEL
py_sec_vault-0.1.6.dist-info/RECORD
