Metadata-Version: 2.1
Name: py-sec-vault
Version: 0.1.6
Summary: Vault implementation in python software (Hashicorp)
Home-page: https://github.com/cisolutions-nl/py-sec-vault
License: MIT
Keywords: vault,hashicorp,security
Author: CISolutions B.V.
Author-email: info@cisolutions.nl
Requires-Python: >=3.9
Classifier: Environment :: Console
Classifier: License :: OSI Approved :: MIT License
Classifier: Operating System :: OS Independent
Classifier: Programming Language :: Python :: 3
Classifier: Programming Language :: Python :: 3.9
Classifier: Programming Language :: Python :: 3.10
Classifier: Programming Language :: Python :: 3.11
Classifier: Topic :: Software Development :: Documentation
Classifier: Topic :: Software Development :: Libraries :: Python Modules
Classifier: Topic :: Software Development :: Quality Assurance
Requires-Dist: requests (==2.31.0)
Project-URL: Repository, https://github.com/cisolutions-nl/py-sec-vault
